sheryanalysis/__init__.py
sheryanalysis/analyzer.py
sheryanalysis/imputer.py
sheryanalysis/logger.py
sheryanalysis/utils.py
sheryanalysis-0.1.0.dist-info/METADATA
sheryanalysis-0.1.0.dist-info/WHEEL
sheryanalysis-0.1.0.dist-info/top_level.txt
sheryanalysis-0.1.0.dist-info/RECORD
